Metadata-Version: 2.1
Name: pranky-shiprocket
Version: 0.1.3
Summary: Python Library for Shiprocket
Home-page: UNKNOWN
Author: Ankit Bhardwaj
License: MIT
Platform: UNKNOWN
